counter/t_ff.v
module t_ff (
    input t, 
    input clk, 
    input rst, 
    output reg q
);
    always @(negedge clk or posedge rst) begin
        if (rst) 
            q <= 1'b0;  
        else 
            q <= ~q;
    end
endmodule

counter/counter1.v
module ripple(
    input rst, clk,
    output wire [3:0] count
); 
t_ff ff0(1'b1, clk, rst, count[0]);   
t_ff ff1(1'b1, count[0], rst, count[1]);  
t_ff ff2(1'b1, count[1], rst, count[2]); 
t_ff ff3(1'b1, count[2], rst, count[3]);  

endmodule


// Test bench code
module ripple_tb;
reg rst;
reg clk;
wire [3:0] count;   
ripple uut(.*);
initial begin
clk = 0;
forever #5 clk = ~clk; 
end
initial begin 
$dumpfile("ripple.vcd");
$dumpvars(0, ripple_tb);
$monitor($time, " counting = %b", count);       
rst = 1; 
#20 rst = 0; 
#500 $finish; 
end 
endmodule

counter/ripple.vcd
$date
	Fri Mar 21 19:01:02 2025
$end
$version
	Icarus Verilog
$end
$timescale
	1s
$end
$scope module ripple_tb $end
$var wire 4 ! count [3:0] $end
$var reg 1 " clk $end
$var reg 1 # rst $end
$scope module uut $end
$var wire 1 " clk $end
$var wire 1 # rst $end
$var wire 4 $ count [3:0] $end
$scope module ff0 $end
$var wire 1 " clk $end
$var wire 1 # rst $end
$var wire 1 % t $end
$var reg 1 & q $end
$upscope $end
$scope module ff1 $end
$var wire 1 ' clk $end
$var wire 1 # rst $end
$var wire 1 ( t $end
$var reg 1 ) q $end
$upscope $end
$scope module ff2 $end
$var wire 1 * clk $end
$var wire 1 # rst $end
$var wire 1 + t $end
$var reg 1 , q $end
$upscope $end
$scope module ff3 $end
$var wire 1 - clk $end
$var wire 1 # rst $end
$var wire 1 . t $end
$var reg 1 / q $end
$upscope $end
$upscope $end
$upscope $end
$enddefinitions $end
$comment Show the parameter values. $end
$dumpall
$end
#0
$dumpvars
0/
1.
0-
0,
1+
0*
0)
1(
0'
0&
1%
b0 $
1#
0"
b0 !
$end
#5
1"
#10
0"
#15
1"
#20
1'
b1 !
b1 $
1&
0"
0#
#25
1"
#30
1*
1)
0'
b10 !
b10 $
0&
0"
#35
1"
#40
1'
b11 !
b11 $
1&
0"
#45
1"
#50
1-
1,
0*
0)
0'
b100 !
b100 $
0&
0"
#55
1"
#60
1'
b101 !
b101 $
1&
0"
#65
1"
#70
1*
1)
0'
b110 !
b110 $
0&
0"
#75
1"
#80
1'
b111 !
b111 $
1&
0"
#85
1"
#90
1/
0-
0,
0*
0)
0'
b1000 !
b1000 $
0&
0"
#95
1"
#100
1'
b1001 !
b1001 $
1&
0"
#105
1"
#110
1*
1)
0'
b1010 !
b1010 $
0&
0"
#115
1"
#120
1'
b1011 !
b1011 $
1&
0"
#125
1"
#130
1-
1,
0*
0)
0'
b1100 !
b1100 $
0&
0"
#135
1"
#140
1'
b1101 !
b1101 $
1&
0"
#145
1"
#150
1*
1)
0'
b1110 !
b1110 $
0&
0"
#155
1"
#160
1'
b1111 !
b1111 $
1&
0"
#165
1"
#170
0/
0-
0,
0*
0)
0'
b0 !
b0 $
0&
0"
#175
1"
#180
1'
b1 !
b1 $
1&
0"
#185
1"
#190
1*
1)
0'
b10 !
b10 $
0&
0"
#195
1"
#200
1'
b11 !
b11 $
1&
0"
#205
1"
#210
1-
1,
0*
0)
0'
b100 !
b100 $
0&
0"
#215
1"
#220
1'
b101 !
b101 $
1&
0"
#225
1"
#230
1*
1)
0'
b110 !
b110 $
0&
0"
#235
1"
#240
1'
b111 !
b111 $
1&
0"
#245
1"
#250
1/
0-
0,
0*
0)
0'
b1000 !
b1000 $
0&
0"
#255
1"
#260
1'
b1001 !
b1001 $
1&
0"
#265
1"
#270
1*
1)
0'
b1010 !
b1010 $
0&
0"
#275
1"
#280
1'
b1011 !
b1011 $
1&
0"
#285
1"
#290
1-
1,
0*
0)
0'
b1100 !
b1100 $
0&
0"
#295
1"
#300
1'
b1101 !
b1101 $
1&
0"
#305
1"
#310
1*
1)
0'
b1110 !
b1110 $
0&
0"
#315
1"
#320
1'
b1111 !
b1111 $
1&
0"
#325
1"
#330
0/
0-
0,
0*
0)
0'
b0 !
b0 $
0&
0"
#335
1"
#340
1'
b1 !
b1 $
1&
0"
#345
1"
#350
1*
1)
0'
b10 !
b10 $
0&
0"
#355
1"
#360
1'
b11 !
b11 $
1&
0"
#365
1"
#370
1-
1,
0*
0)
0'
b100 !
b100 $
0&
0"
#375
1"
#380
1'
b101 !
b101 $
1&
0"
#385
1"
#390
1*
1)
0'
b110 !
b110 $
0&
0"
#395
1"
#400
1'
b111 !
b111 $
1&
0"
#405
1"
#410
1/
0-
0,
0*
0)
0'
b1000 !
b1000 $
0&
0"
#415
1"
#420
1'
b1001 !
b1001 $
1&
0"
#425
1"
#430
1*
1)
0'
b1010 !
b1010 $
0&
0"
#435
1"
#440
1'
b1011 !
b1011 $
1&
0"
#445
1"
#450
1-
1,
0*
0)
0'
b1100 !
b1100 $
0&
0"
#455
1"
#460
1'
b1101 !
b1101 $
1&
0"
#465
1"
#470
1*
1)
0'
b1110 !
b1110 $
0&
0"
#475
1"
#480
1'
b1111 !
b1111 $
1&
0"
#485
1"
#490
0/
0-
0,
0*
0)
0'
b0 !
b0 $
0&
0"
#495
1"
#500
1'
b1 !
b1 $
1&
0"
#505
1"
#510
1*
1)
0'
b10 !
b10 $
0&
0"
#515
1"
#520
1'
b11 !
b11 $
1&
0"
